examples/__init__.py
examples/03relative/__init__.py
examples/03relative/config.py
examples/03relative/main.py
examples/03relative/shapes.py
magicalimport/__init__.py
magicalimport/_fake.py
magicalimport/compat.py
magicalimport-0.9.1.dist-info/LICENSE
magicalimport-0.9.1.dist-info/METADATA
magicalimport-0.9.1.dist-info/WHEEL
magicalimport-0.9.1.dist-info/entry_points.txt
magicalimport-0.9.1.dist-info/top_level.txt
magicalimport-0.9.1.dist-info/RECORD
