Metadata-Version: 2.1
Name: magicalimport
Version: 0.9.1
Summary: importing a module by physical file path
Home-page: https://github.com/podhmo/magicalimport
Author: podhmo
Author-email: ababjam61+github@gmail.com
License: UNKNOWN
Keywords: import,physical address,file path
Platform: UNKNOWN
Classifier: Programming Language :: Python
Classifier: Programming Language :: Python :: Implementation :: CPython
Provides-Extra: docs
Provides-Extra: testing
